{"ghana":[{"gloss":"a republic in West Africa on the Gulf of Guinea","pos":"noun","synonyms":[{"word":"republic of ghana","score":1000},{"word":"gold coast","score":996}]}],"ghastliness":[{"gloss":"the quality of being ghastly","pos":"noun","synonyms":[{"word":"grimness","score":1000},{"word":"gruesomeness","score":996},{"word":"luridness","score":992}]}],"ghatti":[{"gloss":"an Indian gum from the dhawa tree","pos":"noun","synonyms":[{"word":"ghatti gum","score":1000}]}],"ghatti gum":[{"gloss":"an Indian gum from the dhawa tree","pos":"noun","synonyms":[{"word":"ghatti","score":1000}]}],"ghb":[{"gloss":"a club drug available in liquid or powder form is taken orally (frequently combined with alcohol)","pos":"noun","synonyms":[{"word":"gamma hydroxybutyrate","score":1000}]}],"gheg":[{"gloss":"the dialect of Albanian spoken in northern Albania and Yugoslavia","pos":"noun","synonyms":[{"word":"gheg dialect","score":1000}]}],"gheg dialect":[{"gloss":"the dialect of Albanian spoken in northern Albania and Yugoslavia","pos":"noun","synonyms":[{"word":"gheg","score":1000}]}],"ghent":[{"gloss":"port city in northwestern Belgium and industrial center","pos":"noun","synonyms":[{"word":"gent","score":1000},{"word":"gand","score":996}]}],"ghetto blaster":[{"gloss":"a portable stereo","pos":"noun","synonyms":[{"word":"boom box","score":1000}]}],"ghillie":[{"gloss":"a shoe without a tongue and with decorative lacing up the instep","pos":"noun","synonyms":[{"word":"gillie","score":1000}]}],"ghost":[{"gloss":"a mental representation of some haunting experience","pos":"noun","synonyms":[{"word":"shade","score":1000},{"word":"spook","score":996},{"word":"wraith","score":992},{"word":"specter","score":988},{"word":"spectre","score":984}]},{"gloss":"a writer who gives the credit of authorship to someone else","pos":"noun","synonyms":[{"word":"ghostwriter","score":940}]},{"gloss":"a suggestion of some quality","pos":"noun","synonyms":[{"word":"touch","score":820},{"word":"trace","score":816}]},{"gloss":"haunt like a ghost","pos":"verb","synonyms":[{"word":"haunt","score":940},{"word":"obsess","score":936}]},{"gloss":"write for someone else","pos":"verb","synonyms":[{"word":"ghostwrite","score":880}]}],"ghost gum":[{"gloss":"small to medium-sized tree of Australia and Tasmania having smooth white to light-grey bark shedding in patches or strips","pos":"noun","synonyms":[{"word":"snow gum","score":1000},{"word":"white ash","score":996},{"word":"eucalyptus coriacea","score":992},{"word":"eucalyptus pauciflora","score":988}]}],"ghost weed":[{"gloss":"annual spurge of western United States having showy white-bracted flower clusters and very poisonous milk","pos":"noun","synonyms":[{"word":"snow-on-the-mountain","score":1000},{"word":"snow-in-summer","score":996},{"word":"euphorbia marginata","score":992}]}],"ghostfish":[{"gloss":"eellike Atlantic bottom fish with large almost vertical mouth","pos":"noun","synonyms":[{"word":"wrymouth","score":1000},{"word":"cryptacanthodes maculatus","score":996}]}],"ghostliness":[{"gloss":"strangeness by virtue of being mysterious and inspiring fear","pos":"noun","synonyms":[{"word":"eeriness","score":1000}]}],"ghostwriter":[{"gloss":"a writer who gives the credit of authorship to someone else","pos":"noun","synonyms":[{"word":"ghost","score":1000}]}],"ghoul":[{"gloss":"someone who takes bodies from graves and sells them for anatomical dissection","pos":"noun","synonyms":[{"word":"graverobber","score":1000},{"word":"body snatcher","score":996}]}],"ghq":[{"gloss":"military headquarters from which a military commander controls and organizes the forces","pos":"noun","synonyms":[{"word":"command post","score":1000},{"word":"general headquarters","score":996}]}],"ghrf":[{"gloss":"a releasing factor that accelerates the secretion of growth hormone by the anterior pituitary body","pos":"noun","synonyms":[{"word":"growth hormone-releasing factor","score":1000}]}],"ghz":[{"gloss":"1,000,000,000 periods per second","pos":"noun","synonyms":[{"word":"gigahertz","score":1000},{"word":"gigacycle per second","score":996},{"word":"gigacycle","score":992},{"word":"gc","score":988}]}],"ghettoise":[{"gloss":"put in a ghetto","pos":"verb","synonyms":[{"word":"ghettoize","score":1000}]}],"ghettoize":[{"gloss":"put in a ghetto","pos":"verb","synonyms":[{"word":"ghettoise","score":1000}]}],"ghostwrite":[{"gloss":"write for someone else","pos":"verb","synonyms":[{"word":"ghost","score":1000}]}],"ghanaian":[{"gloss":"of or relating to or characteristic of Ghana or its people or language","pos":"adj","synonyms":[{"word":"ghanese","score":1000},{"word":"ghanian","score":996}]}],"ghanese":[{"gloss":"of or relating to or characteristic of Ghana or its people or language","pos":"adj","synonyms":[{"word":"ghanaian","score":1000},{"word":"ghanian","score":996}]}],"ghanian":[{"gloss":"of or relating to or characteristic of Ghana or its people or language","pos":"adj","synonyms":[{"word":"ghanaian","score":1000},{"word":"ghanese","score":996}]}],"ghastly":[{"gloss":"shockingly repellent","pos":"adj","synonyms":[{"word":"grim","score":1000},{"word":"grisly","score":996},{"word":"gruesome","score":992},{"word":"macabre","score":988},{"word":"sick","score":984}]},{"gloss":"gruesomely indicative of death or the dead","pos":"adj","synonyms":[{"word":"charnel","score":940},{"word":"sepulchral","score":936}]}],"ghostlike":[{"gloss":"resembling or characteristic of a phantom","pos":"adj","synonyms":[{"word":"apparitional","score":1000},{"word":"ghostly","score":996},{"word":"phantasmal","score":992},{"word":"spectral","score":988},{"word":"spiritual","score":984}]}],"ghostly":[{"gloss":"resembling or characteristic of a phantom","pos":"adj","synonyms":[{"word":"apparitional","score":1000},{"word":"ghostlike","score":996},{"word":"phantasmal","score":992},{"word":"spectral","score":988},{"word":"spiritual","score":984}]}],"ghoulish":[{"gloss":"suggesting the horror of death and decay","pos":"adj","synonyms":[{"word":"morbid","score":1000}]}]}